.pypirc
CHANGES.txt
MANIFEST.in
README.rst
distribute-0.6.24.tar.gz
setup.py
github_repos_cloner/__init__.py
github_repos_cloner.egg-info/PKG-INFO
github_repos_cloner.egg-info/SOURCES.txt
github_repos_cloner.egg-info/dependency_links.txt
github_repos_cloner.egg-info/entry_points.txt
github_repos_cloner.egg-info/not-zip-safe
github_repos_cloner.egg-info/requires.txt
github_repos_cloner.egg-info/top_level.txt