Metadata-Version: 1.0
Name: github-repos-cloner
Version: 0.0.2
Summary: Clone all the github repos for backup purposes
Home-page: https://github.com/aclark4life/github_repos_cloner
Author: Alex Clark
Author-email: aclark@aclark.net
License: GPL
Keywords: backup clone git organization
Platform: UNKNOWN
Classifier: Environment :: Console
